MCP_Server/__init__.py
MCP_Server/server.py
ableton_mcp-1.0.4.dist-info/licenses/LICENSE
ableton_mcp-1.0.4.dist-info/METADATA
ableton_mcp-1.0.4.dist-info/WHEEL
ableton_mcp-1.0.4.dist-info/entry_points.txt
ableton_mcp-1.0.4.dist-info/top_level.txt
ableton_mcp-1.0.4.dist-info/RECORD
